{"nodes":[{"label":"Steimann (2017)","x":-266.3622741699219,"y":38.52558898925781,"id":"30","attributes":{"comm":"1","year":"2017","author":"Friedrich Steimann","dblp_id":"5a260c0917c44a4ba8a1d86d","description":"\u003ctable\u003e\u003ctr\u003e\u003ctd\u003eAuthor:\u003c/td\u003e\u003ctd\u003eFriedrich Steimann\u003c/td\u003e\u003c/tr\u003e\u003ctr\u003e\u003ctd\u003eTitle:\u003c/td\u003e\u003ctd\u003eRobust projectional editing.\u003c/td\u003e\u003c/tr\u003e\u003ctr\u003e\u003ctd\u003eSource:\u003c/td\u003e\u003ctd\u003eSPLASH \u002717: Conference on Systems, Programming, Languages, and Applications: Software for Humanity\u0026#10;\u0026#9;\u0026#9;      Vancouver\u0026#10;\u0026#9;\u0026#9;      BC\u0026#10;\u0026#9;\u0026#9;      Canada\u0026#10;\u0026#9;\u0026#9;    October, 2017\u003c/td\u003e\u003c/tr\u003e\u003ctr\u003e\u003ctd\u003eYear:\u003c/td\u003e\u003ctd\u003e2017\u003c/td\u003e\u003c/tr\u003e\u003c/table\u003e","Cluster":"1","main":"1","title":"Robust projectional editing.","url":"http://doi.acm.org/10.1145/3136014.3136034"},"color":"rgb(95,198,19)","size":13.076923370361328},{"label":"Yoon (2015)","x":61.44208908081055,"y":35.87443923950195,"id":"19","attributes":{"comm":"1","year":"2015","author":"YoungSeok Yoon","dblp_id":"5736970f6e3b12023e6088e9","description":"\u003ctable\u003e\u003ctr\u003e\u003ctd\u003eAuthor:\u003c/td\u003e\u003ctd\u003eYoungSeok Yoon\u003c/td\u003e\u003c/tr\u003e\u003ctr\u003e\u003ctd\u003eTitle:\u003c/td\u003e\u003ctd\u003eSupporting selective undo in a code editor\u003c/td\u003e\u003c/tr\u003e\u003ctr\u003e\u003ctd\u003eSource:\u003c/td\u003e\u003ctd\u003eICSE\u003c/td\u003e\u003c/tr\u003e\u003ctr\u003e\u003ctd\u003eYear:\u003c/td\u003e\u003ctd\u003e2015\u003c/td\u003e\u003c/tr\u003e\u003c/table\u003e","Cluster":"0","main":"1","title":"Supporting selective undo in a code editor","url":"http://dx.doi.org/10.1109/ICSE.2015.43"},"color":"rgb(198,134,233)","size":11.538461685180664},{"label":"Feiler (1987)","x":-6.232605457305908,"y":-929.0275268554688,"id":"1","attributes":{"comm":"0","year":"1987","author":"P. H. Feiler","dblp_id":"53e9a1c3b7602d9702ab9694","description":"\u003ctable\u003e\u003ctr\u003e\u003ctd\u003eAuthor:\u003c/td\u003e\u003ctd\u003eP. H. Feiler\u003c/td\u003e\u003c/tr\u003e\u003ctr\u003e\u003ctd\u003eTitle:\u003c/td\u003e\u003ctd\u003eRelationship between IDL and structure editor generation technology\u003c/td\u003e\u003c/tr\u003e\u003ctr\u003e\u003ctd\u003eSource:\u003c/td\u003e\u003ctd\u003eSIGPLAN Notices\u003c/td\u003e\u003c/tr\u003e\u003ctr\u003e\u003ctd\u003eYear:\u003c/td\u003e\u003ctd\u003e1987\u003c/td\u003e\u003c/tr\u003e\u003c/table\u003e","Cluster":"3","main":"1","title":"Relationship between IDL and structure editor generation technology","url":"http://dx.doi.org/10.1145/39305.39314"},"color":"rgb(234,134,21)","size":10.0},{"label":"Ko (2006)","x":-35.27934646606445,"y":138.37713623046875,"id":"4","attributes":{"comm":"1","year":"2006","author":"Andrew J. Ko","dblp_id":"53e9a464b7602d9702d82bc7","description":"\u003ctable\u003e\u003ctr\u003e\u003ctd\u003eAuthor:\u003c/td\u003e\u003ctd\u003eAndrew J. Ko\u003c/td\u003e\u003c/tr\u003e\u003ctr\u003e\u003ctd\u003eTitle:\u003c/td\u003e\u003ctd\u003eBarista: An implementation framework for enabling new tools, interaction techniques and views in code editors\u003c/td\u003e\u003c/tr\u003e\u003ctr\u003e\u003ctd\u003eSource:\u003c/td\u003e\u003ctd\u003eCHI\u003c/td\u003e\u003c/tr\u003e\u003ctr\u003e\u003ctd\u003eYear:\u003c/td\u003e\u003ctd\u003e2006\u003c/td\u003e\u003c/tr\u003e\u003c/table\u003e","Cluster":"0","main":"1","title":"Barista: An implementation framework for enabling new tools, interaction techniques and views in code editors","url":"http://dx.doi.org/10.1145/1124772.1124831"},"color":"rgb(198,134,233)","size":30.0},{"label":"Miller (1994)","x":18.331132888793945,"y":53.203651428222656,"id":"7","attributes":{"comm":"1","year":"1994","author":"Philip Miller","dblp_id":"5736961b6e3b12023e52c927","description":"\u003ctable\u003e\u003ctr\u003e\u003ctd\u003eAuthor:\u003c/td\u003e\u003ctd\u003ePhilip Miller\u003c/td\u003e\u003c/tr\u003e\u003ctr\u003e\u003ctd\u003eTitle:\u003c/td\u003e\u003ctd\u003eEvolution of Novice Programming Environments: The Structure Editors of Carnegie Mellon University\u003c/td\u003e\u003c/tr\u003e\u003ctr\u003e\u003ctd\u003eSource:\u003c/td\u003e\u003ctd\u003eInteractive Learning Environments\u003c/td\u003e\u003c/tr\u003e\u003ctr\u003e\u003ctd\u003eYear:\u003c/td\u003e\u003ctd\u003e1994\u003c/td\u003e\u003c/tr\u003e\u003c/table\u003e","Cluster":"0","main":"1","title":"Evolution of Novice Programming Environments: The Structure Editors of Carnegie Mellon University","url":"http://dx.doi.org/10.1080/1049482940040202"},"color":"rgb(198,134,233)","size":17.69230842590332},{"label":"Yoon (2011)","x":18.118501663208008,"y":-23.969219207763672,"id":"2","attributes":{"comm":"1","year":"2011","author":"YoungSeok Yoon","dblp_id":"53e9a202b7602d9702b03df9","description":"\u003ctable\u003e\u003ctr\u003e\u003ctd\u003eAuthor:\u003c/td\u003e\u003ctd\u003eYoungSeok Yoon\u003c/td\u003e\u003c/tr\u003e\u003ctr\u003e\u003ctd\u003eTitle:\u003c/td\u003e\u003ctd\u003eCapturing and analyzing low-level events from the code editor\u003c/td\u003e\u003c/tr\u003e\u003ctr\u003e\u003ctd\u003eSource:\u003c/td\u003e\u003ctd\u003ePLATEAU\u003c/td\u003e\u003c/tr\u003e\u003ctr\u003e\u003ctd\u003eYear:\u003c/td\u003e\u003ctd\u003e2011\u003c/td\u003e\u003c/tr\u003e\u003c/table\u003e","Cluster":"0","main":"1","title":"Capturing and analyzing low-level events from the code editor","url":"http://dx.doi.org/10.1145/2089155.2089163"},"color":"rgb(198,134,233)","size":11.538461685180664},{"label":"Baader (2015)","x":-291.97418212890625,"y":0.47913503646850586,"id":"18","attributes":{"comm":"1","year":"2015","author":"Siemen Baader","dblp_id":"573697036e3b12023e5fd552","description":"\u003ctable\u003e\u003ctr\u003e\u003ctd\u003eAuthor:\u003c/td\u003e\u003ctd\u003eSiemen Baader\u003c/td\u003e\u003c/tr\u003e\u003ctr\u003e\u003ctd\u003eTitle:\u003c/td\u003e\u003ctd\u003eSketchCode \u0026#8211; An Extensible Code Editor for Crafting Software\u003c/td\u003e\u003c/tr\u003e\u003ctr\u003e\u003ctd\u003eSource:\u003c/td\u003e\u003ctd\u003eLecture Notes in Computer Science\u003c/td\u003e\u003c/tr\u003e\u003ctr\u003e\u003ctd\u003eYear:\u003c/td\u003e\u003ctd\u003e2015\u003c/td\u003e\u003c/tr\u003e\u003c/table\u003e","Cluster":"1","main":"1","title":"SketchCode \u0026#8211; An Extensible Code Editor for Crafting Software","url":"http://dx.doi.org/10.1007/978-3-319-18425-8_18"},"color":"rgb(95,198,19)","size":10.0},{"label":"Berger (2016)","x":-177.9371337890625,"y":-12.00894832611084,"id":"23","attributes":{"comm":"1","year":"2016","author":"Thorsten Berger","dblp_id":"58437783ac44360f1084234a","description":"\u003ctable\u003e\u003ctr\u003e\u003ctd\u003eAuthor:\u003c/td\u003e\u003ctd\u003eThorsten Berger\u003c/td\u003e\u003c/tr\u003e\u003ctr\u003e\u003ctd\u003eTitle:\u003c/td\u003e\u003ctd\u003eEfficiency of projectional editing: a controlled experiment.\u003c/td\u003e\u003c/tr\u003e\u003ctr\u003e\u003ctd\u003eSource:\u003c/td\u003e\u003ctd\u003eSIGSOFT FSE\u003c/td\u003e\u003c/tr\u003e\u003ctr\u003e\u003ctd\u003eYear:\u003c/td\u003e\u003ctd\u003e2016\u003c/td\u003e\u003c/tr\u003e\u003c/table\u003e","Cluster":"1","main":"1","title":"Efficiency of projectional editing: a controlled experiment.","url":"http://dx.doi.org/10.1145/2950290.2950315"},"color":"rgb(95,198,19)","size":22.307693481445312},{"label":"Mészáros (2019)","x":-305.7377624511719,"y":257.30645751953125,"id":"37","attributes":{"comm":"2","year":"2019","author":"M\u0026#243;nika M\u0026#233;sz\u0026#225;ros","dblp_id":"5d4bf3b63a55ac7a9c4c62ad","description":"\u003ctable\u003e\u003ctr\u003e\u003ctd\u003eAuthor:\u003c/td\u003e\u003ctd\u003eM\u0026#243;nika M\u0026#233;sz\u0026#225;ros\u003c/td\u003e\u003c/tr\u003e\u003ctr\u003e\u003ctd\u003eTitle:\u003c/td\u003e\u003ctd\u003eDelivering comprehension features into source code editors through LSP.\u003c/td\u003e\u003c/tr\u003e\u003ctr\u003e\u003ctd\u003eSource:\u003c/td\u003e\u003ctd\u003eMIPRO\u003c/td\u003e\u003c/tr\u003e\u003ctr\u003e\u003ctd\u003eYear:\u003c/td\u003e\u003ctd\u003e2019\u003c/td\u003e\u003c/tr\u003e\u003c/table\u003e","Cluster":"2","main":"1","title":"Delivering comprehension features into source code editors through LSP.","url":"https://doi.org/10.23919/MIPRO.2019.8756695"},"color":"rgb(0,202,255)","size":10.0},{"label":"Henley (2014)","x":582.0200805664062,"y":-618.0580444335938,"id":"22","attributes":{"comm":"3","year":"2014","author":"Austin Z. Henley","dblp_id":"53e9a6a6b7602d9702fd9db5","description":"\u003ctable\u003e\u003ctr\u003e\u003ctd\u003eAuthor:\u003c/td\u003e\u003ctd\u003eAustin Z. Henley\u003c/td\u003e\u003c/tr\u003e\u003ctr\u003e\u003ctd\u003eTitle:\u003c/td\u003e\u003ctd\u003eThe patchworks code editor: toward faster navigation with less code arranging and fewer navigation mistakes\u003c/td\u003e\u003c/tr\u003e\u003ctr\u003e\u003ctd\u003eSource:\u003c/td\u003e\u003ctd\u003eCHI\u003c/td\u003e\u003c/tr\u003e\u003ctr\u003e\u003ctd\u003eYear:\u003c/td\u003e\u003ctd\u003e2014\u003c/td\u003e\u003c/tr\u003e\u003c/table\u003e","Cluster":"4","main":"1","title":"The patchworks code editor: toward faster navigation with less code arranging and fewer navigation mistakes","url":"http://dx.doi.org/10.1145/2556288.2557073"},"color":"rgb(46,144,114)","size":11.538461685180664},{"label":"Henley (2016)","x":559.6804809570312,"y":-668.0250244140625,"id":"21","attributes":{"comm":"3","year":"2016","author":"Austin Z. Henley","dblp_id":"5843776cac44360f1083eca4","description":"\u003ctable\u003e\u003ctr\u003e\u003ctd\u003eAuthor:\u003c/td\u003e\u003ctd\u003eAustin Z. Henley\u003c/td\u003e\u003c/tr\u003e\u003ctr\u003e\u003ctd\u003eTitle:\u003c/td\u003e\u003ctd\u003eDesigning affordances for navigating information spaces in code editors.\u003c/td\u003e\u003c/tr\u003e\u003ctr\u003e\u003ctd\u003eSource:\u003c/td\u003e\u003ctd\u003eSymposium on Visual Languages and Human Centric Computing VL HCC\u003c/td\u003e\u003c/tr\u003e\u003ctr\u003e\u003ctd\u003eYear:\u003c/td\u003e\u003ctd\u003e2016\u003c/td\u003e\u003c/tr\u003e\u003c/table\u003e","Cluster":"4","main":"1","title":"Designing affordances for navigating information spaces in code editors.","url":"http://dx.doi.org/10.1109/VLHCC.2016.7739703"},"color":"rgb(46,144,114)","size":10.0},{"label":"Ko (2005)","x":-11.975652694702148,"y":9.148396492004395,"id":"6","attributes":{"comm":"1","year":"2005","author":"Andrew J. Ko","dblp_id":"53e9af9fb7602d97039e8b6e","description":"\u003ctable\u003e\u003ctr\u003e\u003ctd\u003eAuthor:\u003c/td\u003e\u003ctd\u003eAndrew J. Ko\u003c/td\u003e\u003c/tr\u003e\u003ctr\u003e\u003ctd\u003eTitle:\u003c/td\u003e\u003ctd\u003eCitrus: a language and toolkit for simplifying the creation of structured editors for code and data\u003c/td\u003e\u003c/tr\u003e\u003ctr\u003e\u003ctd\u003eSource:\u003c/td\u003e\u003ctd\u003eUIST\u003c/td\u003e\u003c/tr\u003e\u003ctr\u003e\u003ctd\u003eYear:\u003c/td\u003e\u003ctd\u003e2005\u003c/td\u003e\u003c/tr\u003e\u003c/table\u003e","Cluster":"0","main":"1","title":"Citrus: a language and toolkit for simplifying the creation of structured editors for code and data","url":"http://dx.doi.org/10.1145/1095034.1095037"},"color":"rgb(198,134,233)","size":13.076923370361328},{"label":"Asenov (2014)","x":-123.24256134033203,"y":184.0485382080078,"id":"14","attributes":{"comm":"1","year":"2014","author":"Dimitar Asenov","dblp_id":"5550467245ce0a409eb5e94c","description":"\u003ctable\u003e\u003ctr\u003e\u003ctd\u003eAuthor:\u003c/td\u003e\u003ctd\u003eDimitar Asenov\u003c/td\u003e\u003c/tr\u003e\u003ctr\u003e\u003ctd\u003eTitle:\u003c/td\u003e\u003ctd\u003eEnvision: A fast and flexible visual code editor with fluid interactions (Overview).\u003c/td\u003e\u003c/tr\u003e\u003ctr\u003e\u003ctd\u003eSource:\u003c/td\u003e\u003ctd\u003eSymposium on Visual Languages and Human Centric Computing VL HCC\u003c/td\u003e\u003c/tr\u003e\u003ctr\u003e\u003ctd\u003eYear:\u003c/td\u003e\u003ctd\u003e2014\u003c/td\u003e\u003c/tr\u003e\u003c/table\u003e","Cluster":"2","main":"1","title":"Envision: A fast and flexible visual code editor with fluid interactions (Overview).","url":"http://dx.doi.org/10.1109/VLHCC.2014.6883014"},"color":"rgb(0,202,255)","size":14.615385055541992},{"label":"Santos (2020)","x":-123.72081756591797,"y":66.61666870117188,"id":"41","attributes":{"comm":"1","year":"2020","author":"Andr\u0026#233; L. Santos","dblp_id":"5f36634691e0114ccd02c5cb","description":"\u003ctable\u003e\u003ctr\u003e\u003ctd\u003eAuthor:\u003c/td\u003e\u003ctd\u003eAndr\u0026#233; L. Santos\u003c/td\u003e\u003c/tr\u003e\u003ctr\u003e\u003ctd\u003eTitle:\u003c/td\u003e\u003ctd\u003eJavardise - a structured code editor for programming pedagogy in Java.\u003c/td\u003e\u003c/tr\u003e\u003ctr\u003e\u003ctd\u003eSource:\u003c/td\u003e\u003ctd\u003eProgramming\u003c/td\u003e\u003c/tr\u003e\u003ctr\u003e\u003ctd\u003eYear:\u003c/td\u003e\u003ctd\u003e2020\u003c/td\u003e\u003c/tr\u003e\u003c/table\u003e","Cluster":"1","main":"1","title":"Javardise - a structured code editor for programming pedagogy in Java.","url":"https://doi.org/10.1145/3397537.3397561"},"color":"rgb(95,198,19)","size":14.615385055541992},{"label":"gomolka (2011)","x":75.52416229248047,"y":171.3660430908203,"id":"16","attributes":{"comm":"1","year":"2011","author":"andreas gomolka","dblp_id":"56d814afdabfae2eee696d2f","description":"\u003ctable\u003e\u003ctr\u003e\u003ctd\u003eAuthor:\u003c/td\u003e\u003ctd\u003eandreas gomolka\u003c/td\u003e\u003c/tr\u003e\u003ctr\u003e\u003ctd\u003eTitle:\u003c/td\u003e\u003ctd\u003eStructure Editors: Old Hat or Future Vision?\u003c/td\u003e\u003c/tr\u003e\u003ctr\u003e\u003ctd\u003eSource:\u003c/td\u003e\u003ctd\u003eENASE (Selected Papers)\u003c/td\u003e\u003c/tr\u003e\u003ctr\u003e\u003ctd\u003eYear:\u003c/td\u003e\u003ctd\u003e2011\u003c/td\u003e\u003c/tr\u003e\u003c/table\u003e","Cluster":"0","main":"1","title":"Structure Editors: Old Hat or Future Vision?","url":"http://dx.doi.org/10.1007/978-3-642-32341-6_6"},"color":"rgb(198,134,233)","size":10.0},{"label":"clark (2015)","x":-250.71604919433594,"y":-118.4803237915039,"id":"25","attributes":{"comm":"1","year":"2015","author":"tony clark","dblp_id":"573696096e3b12023e51cccc","description":"\u003ctable\u003e\u003ctr\u003e\u003ctd\u003eAuthor:\u003c/td\u003e\u003ctd\u003etony clark\u003c/td\u003e\u003c/tr\u003e\u003ctr\u003e\u003ctd\u003eTitle:\u003c/td\u003e\u003ctd\u003eA General Architecture for Heterogeneous Language Engineering and Projectional Editor Support\u003c/td\u003e\u003c/tr\u003e\u003ctr\u003e\u003ctd\u003eSource:\u003c/td\u003e\u003ctd\u003eCoRR\u003c/td\u003e\u003c/tr\u003e\u003ctr\u003e\u003ctd\u003eYear:\u003c/td\u003e\u003ctd\u003e2015\u003c/td\u003e\u003c/tr\u003e\u003c/table\u003e","Cluster":"1","main":"1","title":"A General Architecture for Heterogeneous Language Engineering and Projectional Editor Support","url":"http://dx.doi.org/10.1145/2997364.2997365"},"color":"rgb(95,198,19)","size":10.0},{"label":"Behringer (2017)","x":-303.3512268066406,"y":-41.38176345825195,"id":"27","attributes":{"comm":"1","year":"2017","author":"Benjamin Behringer","dblp_id":"599c7bea601a182cd2773327","description":"\u003ctable\u003e\u003ctr\u003e\u003ctd\u003eAuthor:\u003c/td\u003e\u003ctd\u003eBenjamin Behringer\u003c/td\u003e\u003c/tr\u003e\u003ctr\u003e\u003ctd\u003eTitle:\u003c/td\u003e\u003ctd\u003ePEoPL: projectional editing of product lines.\u003c/td\u003e\u003c/tr\u003e\u003ctr\u003e\u003ctd\u003eSource:\u003c/td\u003e\u003ctd\u003eICSE\u003c/td\u003e\u003c/tr\u003e\u003ctr\u003e\u003ctd\u003eYear:\u003c/td\u003e\u003ctd\u003e2017\u003c/td\u003e\u003c/tr\u003e\u003c/table\u003e","Cluster":"1","main":"1","title":"PEoPL: projectional editing of product lines.","url":"http://doi.ieeecomputersociety.org/10.1109/ICSE.2017.58"},"color":"rgb(95,198,19)","size":16.153846740722656},{"label":"Kaiser (1988)","x":7.1746826171875,"y":-878.6106567382812,"id":"0","attributes":{"comm":"0","year":"1988","author":"Gail E. Kaiser","dblp_id":"53e9997eb7602d97021bcbd2","description":"\u003ctable\u003e\u003ctr\u003e\u003ctd\u003eAuthor:\u003c/td\u003e\u003ctd\u003eGail E. Kaiser\u003c/td\u003e\u003c/tr\u003e\u003ctr\u003e\u003ctd\u003eTitle:\u003c/td\u003e\u003ctd\u003eA retrospective on DOSE: an interpretive approach to structure editor generation\u003c/td\u003e\u003c/tr\u003e\u003ctr\u003e\u003ctd\u003eSource:\u003c/td\u003e\u003ctd\u003eSoftw., Pract. Exper.\u003c/td\u003e\u003c/tr\u003e\u003ctr\u003e\u003ctd\u003eYear:\u003c/td\u003e\u003ctd\u003e1988\u003c/td\u003e\u003c/tr\u003e\u003c/table\u003e","Cluster":"3","main":"1","title":"A retrospective on DOSE: an interpretive approach to structure editor generation","url":"http://dx.doi.org/10.1002/spe.4380180803"},"color":"rgb(234,134,21)","size":11.538461685180664},{"label":"Garlan (1984)","x":28.175073623657227,"y":167.11459350585938,"id":"5","attributes":{"comm":"1","year":"1984","author":"David B. Garlan","dblp_id":"53e9ad92b7602d970378beba","description":"\u003ctable\u003e\u003ctr\u003e\u003ctd\u003eAuthor:\u003c/td\u003e\u003ctd\u003eDavid B. Garlan\u003c/td\u003e\u003c/tr\u003e\u003ctr\u003e\u003ctd\u003eTitle:\u003c/td\u003e\u003ctd\u003eGNOME: An introductory programming environment based on a family of structure editors\u003c/td\u003e\u003c/tr\u003e\u003ctr\u003e\u003ctd\u003eSource:\u003c/td\u003e\u003ctd\u003eSoftware Development Environments\u003c/td\u003e\u003c/tr\u003e\u003ctr\u003e\u003ctd\u003eYear:\u003c/td\u003e\u003ctd\u003e1984\u003c/td\u003e\u003c/tr\u003e\u003c/table\u003e","Cluster":"0","main":"1","title":"GNOME: An introductory programming environment based on a family of structure editors","url":"http://dx.doi.org/10.1145/390011.808250"},"color":"rgb(198,134,233)","size":14.615385055541992},{"label":"Voelter (2014)","x":-312.4119873046875,"y":49.729610443115234,"id":"12","attributes":{"comm":"1","year":"2014","author":"Markus Voelter","dblp_id":"5550447845ce0a409eb4e0ea","description":"\u003ctable\u003e\u003ctr\u003e\u003ctd\u003eAuthor:\u003c/td\u003e\u003ctd\u003eMarkus Voelter\u003c/td\u003e\u003c/tr\u003e\u003ctr\u003e\u003ctd\u003eTitle:\u003c/td\u003e\u003ctd\u003eSupporting Diverse Notations in MPS\u0027 Projectional Editor.\u003c/td\u003e\u003c/tr\u003e\u003ctr\u003e\u003ctd\u003eSource:\u003c/td\u003e\u003ctd\u003eGEMOC@MoDELS\u003c/td\u003e\u003c/tr\u003e\u003ctr\u003e\u003ctd\u003eYear:\u003c/td\u003e\u003ctd\u003e2014\u003c/td\u003e\u003c/tr\u003e\u003c/table\u003e","Cluster":"1","main":"1","title":"Supporting Diverse Notations in MPS\u0027 Projectional Editor.","url":"http://dx.doi.org/10.1007/BF01415893"},"color":"rgb(95,198,19)","size":13.076923370361328},{"label":"Jacob (2010)","x":-170.669921875,"y":134.416259765625,"id":"10","attributes":{"comm":"2","year":"2010","author":"Ferosh Jacob","dblp_id":"53e9b7c7b7602d9704371fee","description":"\u003ctable\u003e\u003ctr\u003e\u003ctd\u003eAuthor:\u003c/td\u003e\u003ctd\u003eFerosh Jacob\u003c/td\u003e\u003c/tr\u003e\u003ctr\u003e\u003ctd\u003eTitle:\u003c/td\u003e\u003ctd\u003eActively comparing clones inside the code editor\u003c/td\u003e\u003c/tr\u003e\u003ctr\u003e\u003ctd\u003eSource:\u003c/td\u003e\u003ctd\u003eIWSC\u003c/td\u003e\u003c/tr\u003e\u003ctr\u003e\u003ctd\u003eYear:\u003c/td\u003e\u003ctd\u003e2010\u003c/td\u003e\u003c/tr\u003e\u003c/table\u003e","Cluster":"2","main":"1","title":"Actively comparing clones inside the code editor","url":"http://dx.doi.org/10.1145/1808901.1808903"},"color":"rgb(0,202,255)","size":11.538461685180664},{"label":"Goto (2017)","x":-615.9056396484375,"y":871.14794921875,"id":"31","attributes":{"comm":"4","year":"2017","author":"Osamu Goto","dblp_id":"5a260c4c17c44a4ba8a27acf","description":"\u003ctable\u003e\u003ctr\u003e\u003ctd\u003eAuthor:\u003c/td\u003e\u003ctd\u003eOsamu Goto\u003c/td\u003e\u003c/tr\u003e\u003ctr\u003e\u003ctd\u003eTitle:\u003c/td\u003e\u003ctd\u003eA Block-Based Structure Editor for the English Language.\u003c/td\u003e\u003c/tr\u003e\u003ctr\u003e\u003ctd\u003eSource:\u003c/td\u003e\u003ctd\u003eADVANCES IN NETWORK-BASED INFORMATION SYSTEMS, NBIS-2017\u003c/td\u003e\u003c/tr\u003e\u003ctr\u003e\u003ctd\u003eYear:\u003c/td\u003e\u003ctd\u003e2017\u003c/td\u003e\u003c/tr\u003e\u003c/table\u003e","Cluster":"5","main":"1","title":"A Block-Based Structure Editor for the English Language.","url":"https://doi.org/10.1007/978-3-319-65521-5_96"},"color":"rgb(255,92,129)","size":10.0},{"label":"Goldenson (1986)","x":116.96050262451172,"y":28.15987777709961,"id":"17","attributes":{"comm":"1","year":"1986","author":"Dennis R. Goldenson","dblp_id":"53e9ba90b7602d97046b911c","description":"\u003ctable\u003e\u003ctr\u003e\u003ctd\u003eAuthor:\u003c/td\u003e\u003ctd\u003eDennis R. Goldenson\u003c/td\u003e\u003c/tr\u003e\u003ctr\u003e\u003ctd\u003eTitle:\u003c/td\u003e\u003ctd\u003eIntegrated programming environments based on structure editing (panel session)\u003c/td\u003e\u003c/tr\u003e\u003ctr\u003e\u003ctd\u003eSource:\u003c/td\u003e\u003ctd\u003eACM Conference on Computer Science\u003c/td\u003e\u003c/tr\u003e\u003ctr\u003e\u003ctd\u003eYear:\u003c/td\u003e\u003ctd\u003e1986\u003c/td\u003e\u003c/tr\u003e\u003c/table\u003e","Cluster":"0","main":"1","title":"Integrated programming environments based on structure editing (panel session)","url":"http://dx.doi.org/10.1145/324634.325459"},"color":"rgb(198,134,233)","size":10.0},{"label":"Sulír (2018)","x":-227.87118530273438,"y":191.18482971191406,"id":"34","attributes":{"comm":"2","year":"2018","author":"Mat\u0026#250;s Sul\u0026#237;r","dblp_id":"5c38b530df5b8c0b3c87e673","description":"\u003ctable\u003e\u003ctr\u003e\u003ctd\u003eAuthor:\u003c/td\u003e\u003ctd\u003eMat\u0026#250;s Sul\u0026#237;r\u003c/td\u003e\u003c/tr\u003e\u003ctr\u003e\u003ctd\u003eTitle:\u003c/td\u003e\u003ctd\u003eVisual augmentation of source code editors: A systematic mapping study.\u003c/td\u003e\u003c/tr\u003e\u003ctr\u003e\u003ctd\u003eSource:\u003c/td\u003e\u003ctd\u003eJournal of Visual Languages \u0026#38; Computing\u003c/td\u003e\u003c/tr\u003e\u003ctr\u003e\u003ctd\u003eYear:\u003c/td\u003e\u003ctd\u003e2018\u003c/td\u003e\u003c/tr\u003e\u003c/table\u003e","Cluster":"2","main":"1","title":"Visual augmentation of source code editors: A systematic mapping study.","url":"http://dx.doi.org/10.1016/j.jvlc.2018.10.001"},"color":"rgb(0,202,255)","size":16.153846740722656},{"label":"Henley (2017)","x":603.97265625,"y":-567.8887329101562,"id":"26","attributes":{"comm":"3","year":"2017","author":"Austin Z. Henley","dblp_id":"599c7b89601a182cd2745128","description":"\u003ctable\u003e\u003ctr\u003e\u003ctd\u003eAuthor:\u003c/td\u003e\u003ctd\u003eAustin Z. Henley\u003c/td\u003e\u003c/tr\u003e\u003ctr\u003e\u003ctd\u003eTitle:\u003c/td\u003e\u003ctd\u003eToward Principles for the Design of Navigation Affordances in Code Editors: An Empirical Investigation.\u003c/td\u003e\u003c/tr\u003e\u003ctr\u003e\u003ctd\u003eSource:\u003c/td\u003e\u003ctd\u003eCHI\u003c/td\u003e\u003c/tr\u003e\u003ctr\u003e\u003ctd\u003eYear:\u003c/td\u003e\u003ctd\u003e2017\u003c/td\u003e\u003c/tr\u003e\u003c/table\u003e","Cluster":"4","main":"1","title":"Toward Principles for the Design of Navigation Affordances in Code Editors: An Empirical Investigation.","url":"http://doi.acm.org/10.1145/3025453.3025645"},"color":"rgb(46,144,114)","size":10.0},{"label":"Hempel (2018)","x":-23.2115478515625,"y":75.077392578125,"id":"36","attributes":{"comm":"1","year":"2018","author":"Brian Hempel","dblp_id":"5c757436f56def979891fc9f","description":"\u003ctable\u003e\u003ctr\u003e\u003ctd\u003eAuthor:\u003c/td\u003e\u003ctd\u003eBrian Hempel\u003c/td\u003e\u003c/tr\u003e\u003ctr\u003e\u003ctd\u003eTitle:\u003c/td\u003e\u003ctd\u003eD euce : a lightweight user interface for structured editing\u003c/td\u003e\u003c/tr\u003e\u003ctr\u003e\u003ctd\u003eSource:\u003c/td\u003e\u003ctd\u003einternational conference on software engineering\u003c/td\u003e\u003c/tr\u003e\u003ctr\u003e\u003ctd\u003eYear:\u003c/td\u003e\u003ctd\u003e2018\u003c/td\u003e\u003c/tr\u003e\u003c/table\u003e","Cluster":"0","main":"1","title":"D euce : a lightweight user interface for structured editing","url":""},"color":"rgb(198,134,233)","size":11.538461685180664},{"label":"Voelter (2016)","x":-247.60267639160156,"y":-18.666467666625977,"id":"24","attributes":{"comm":"1","year":"2016","author":"Markus Voelter","dblp_id":"58d83045d649053542fe833a","description":"\u003ctable\u003e\u003ctr\u003e\u003ctd\u003eAuthor:\u003c/td\u003e\u003ctd\u003eMarkus Voelter\u003c/td\u003e\u003c/tr\u003e\u003ctr\u003e\u003ctd\u003eTitle:\u003c/td\u003e\u003ctd\u003eEfficient development of consistent projectional editors using grammar cells.\u003c/td\u003e\u003c/tr\u003e\u003ctr\u003e\u003ctd\u003eSource:\u003c/td\u003e\u003ctd\u003eSLE\u003c/td\u003e\u003c/tr\u003e\u003ctr\u003e\u003ctd\u003eYear:\u003c/td\u003e\u003ctd\u003e2016\u003c/td\u003e\u003c/tr\u003e\u003c/table\u003e","Cluster":"1","main":"1","title":"Efficient development of consistent projectional editors using grammar cells.","url":"http://dx.doi.org/10.1145/2997364.2997365"},"color":"rgb(95,198,19)","size":20.76923179626465},{"label":"Beckmann (2020)","x":-129.8572998046875,"y":-44.266883850097656,"id":"39","attributes":{"comm":"1","year":"2020","author":"Tom Beckmann","dblp_id":"5f36634691e0114ccd02c5a9","description":"\u003ctable\u003e\u003ctr\u003e\u003ctd\u003eAuthor:\u003c/td\u003e\u003ctd\u003eTom Beckmann\u003c/td\u003e\u003c/tr\u003e\u003ctr\u003e\u003ctd\u003eTitle:\u003c/td\u003e\u003ctd\u003eEfficient editing in a tree-oriented projectional editor.\u003c/td\u003e\u003c/tr\u003e\u003ctr\u003e\u003ctd\u003eSource:\u003c/td\u003e\u003ctd\u003eProgramming\u003c/td\u003e\u003c/tr\u003e\u003ctr\u003e\u003ctd\u003eYear:\u003c/td\u003e\u003ctd\u003e2020\u003c/td\u003e\u003c/tr\u003e\u003c/table\u003e","Cluster":"1","main":"1","title":"Efficient editing in a tree-oriented projectional editor.","url":"https://doi.org/10.1145/3397537.3398477"},"color":"rgb(95,198,19)","size":13.076923370361328},{"label":"Caplinger (1985)","x":109.01496124267578,"y":233.40335083007812,"id":"9","attributes":{"comm":"1","year":"1985","author":"Michael Caplinger","dblp_id":"53e9b26fb7602d9703d11e00","description":"\u003ctable\u003e\u003ctr\u003e\u003ctd\u003eAuthor:\u003c/td\u003e\u003ctd\u003eMichael Caplinger\u003c/td\u003e\u003c/tr\u003e\u003ctr\u003e\u003ctd\u003eTitle:\u003c/td\u003e\u003ctd\u003eStructured Editor Support for Modularity and Data Abstraction\u003c/td\u003e\u003c/tr\u003e\u003ctr\u003e\u003ctd\u003eSource:\u003c/td\u003e\u003ctd\u003eSLIPE \u002785 Proceedings of the ACM SIGPLAN 85 symposium on Language issues in programming environments\u003c/td\u003e\u003c/tr\u003e\u003ctr\u003e\u003ctd\u003eYear:\u003c/td\u003e\u003ctd\u003e1985\u003c/td\u003e\u003c/tr\u003e\u003c/table\u003e","Cluster":"0","main":"1","title":"Structured Editor Support for Modularity and Data Abstraction","url":"http://dx.doi.org/10.1145/800225.806835"},"color":"rgb(198,134,233)","size":10.0},{"label":"Beckmann (2020)","x":-133.53665161132812,"y":19.47523307800293,"id":"40","attributes":{"comm":"1","year":"2020","author":"Tom Beckmann","dblp_id":"5f36634691e0114ccd02c5aa","description":"\u003ctable\u003e\u003ctr\u003e\u003ctd\u003eAuthor:\u003c/td\u003e\u003ctd\u003eTom Beckmann\u003c/td\u003e\u003c/tr\u003e\u003ctr\u003e\u003ctd\u003eTitle:\u003c/td\u003e\u003ctd\u003eVisual design for a tree-oriented projectional editor.\u003c/td\u003e\u003c/tr\u003e\u003ctr\u003e\u003ctd\u003eSource:\u003c/td\u003e\u003ctd\u003eProgramming\u003c/td\u003e\u003c/tr\u003e\u003ctr\u003e\u003ctd\u003eYear:\u003c/td\u003e\u003ctd\u003e2020\u003c/td\u003e\u003c/tr\u003e\u003c/table\u003e","Cluster":"1","main":"1","title":"Visual design for a tree-oriented projectional editor.","url":"https://doi.org/10.1145/3397537.3397560"},"color":"rgb(95,198,19)","size":14.615385055541992},{"label":"Cowlishaw (1987)","x":-261.79010009765625,"y":286.3260498046875,"id":"35","attributes":{"comm":"2","year":"1987","author":"M. F. Cowlishaw","dblp_id":"53e9b102b7602d9703b7c92a","description":"\u003ctable\u003e\u003ctr\u003e\u003ctd\u003eAuthor:\u003c/td\u003e\u003ctd\u003eM. F. Cowlishaw\u003c/td\u003e\u003c/tr\u003e\u003ctr\u003e\u003ctd\u003eTitle:\u003c/td\u003e\u003ctd\u003eLEXX\u0026#8212;a programmable structured editor\u003c/td\u003e\u003c/tr\u003e\u003ctr\u003e\u003ctd\u003eSource:\u003c/td\u003e\u003ctd\u003eIBM Journal of Research and Development\u003c/td\u003e\u003c/tr\u003e\u003ctr\u003e\u003ctd\u003eYear:\u003c/td\u003e\u003ctd\u003e1987\u003c/td\u003e\u003c/tr\u003e\u003c/table\u003e","Cluster":"2","main":"1","title":"LEXX\u0026#8212;a programmable structured editor","url":"http://dx.doi.org/10.1147/rd.311.0073"},"color":"rgb(0,202,255)","size":10.0},{"label":"Ko (2005)","x":-68.43798065185547,"y":37.209590911865234,"id":"3","attributes":{"comm":"1","year":"2005","author":"Andrew J. Ko","dblp_id":"53e9b3dbb7602d9703ecb6f2","description":"\u003ctable\u003e\u003ctr\u003e\u003ctd\u003eAuthor:\u003c/td\u003e\u003ctd\u003eAndrew J. Ko\u003c/td\u003e\u003c/tr\u003e\u003ctr\u003e\u003ctd\u003eTitle:\u003c/td\u003e\u003ctd\u003eDesign requirements for more flexible structured editors from a study of programmers\u0027 text editing\u003c/td\u003e\u003c/tr\u003e\u003ctr\u003e\u003ctd\u003eSource:\u003c/td\u003e\u003ctd\u003eCHI Extended Abstracts\u003c/td\u003e\u003c/tr\u003e\u003ctr\u003e\u003ctd\u003eYear:\u003c/td\u003e\u003ctd\u003e2005\u003c/td\u003e\u003c/tr\u003e\u003c/table\u003e","Cluster":"0","main":"1","title":"Design requirements for more flexible structured editors from a study of programmers\u0027 text editing","url":"http://dx.doi.org/10.1145/1056808.1056965"},"color":"rgb(198,134,233)","size":23.846153259277344},{"label":"Holsapple (1992)","x":21.088544845581055,"y":-829.1422729492188,"id":"11","attributes":{"comm":"0","year":"1992","author":"C. W. Holsapple","dblp_id":"53e9badfb7602d970470fcb1","description":"\u003ctable\u003e\u003ctr\u003e\u003ctd\u003eAuthor:\u003c/td\u003e\u003ctd\u003eC. W. Holsapple\u003c/td\u003e\u003c/tr\u003e\u003ctr\u003e\u003ctd\u003eTitle:\u003c/td\u003e\u003ctd\u003eGenerating structure editor interfaces for OR procedures\u003c/td\u003e\u003c/tr\u003e\u003ctr\u003e\u003ctd\u003eSource:\u003c/td\u003e\u003ctd\u003eMath. Meth. of OR\u003c/td\u003e\u003c/tr\u003e\u003ctr\u003e\u003ctd\u003eYear:\u003c/td\u003e\u003ctd\u003e1992\u003c/td\u003e\u003c/tr\u003e\u003c/table\u003e","Cluster":"3","main":"1","title":"Generating structure editor interfaces for OR procedures","url":"http://dx.doi.org/10.1007/BF01415893"},"color":"rgb(234,134,21)","size":10.0},{"label":"Asenov (2013)","x":-63.008792877197266,"y":221.80142211914062,"id":"15","attributes":{"comm":"1","year":"2013","author":"Dimitar Asenov","dblp_id":"558be44fe4b02b9f07a3dceb","description":"\u003ctable\u003e\u003ctr\u003e\u003ctd\u003eAuthor:\u003c/td\u003e\u003ctd\u003eDimitar Asenov\u003c/td\u003e\u003c/tr\u003e\u003ctr\u003e\u003ctd\u003eTitle:\u003c/td\u003e\u003ctd\u003eCustomizing the visualization and interaction for embedded domain-specific languages in a structured editor\u003c/td\u003e\u003c/tr\u003e\u003ctr\u003e\u003ctd\u003eSource:\u003c/td\u003e\u003ctd\u003eVisual Languages and Human-Centric Computing\u003c/td\u003e\u003c/tr\u003e\u003ctr\u003e\u003ctd\u003eYear:\u003c/td\u003e\u003ctd\u003e2013\u003c/td\u003e\u003c/tr\u003e\u003c/table\u003e","Cluster":"2","main":"1","title":"Customizing the visualization and interaction for embedded domain-specific languages in a structured editor","url":"http://dx.doi.org/10.1109/VLHCC.2013.6645255"},"color":"rgb(0,202,255)","size":11.538461685180664},{"label":"Völter (2014)","x":-209.7811279296875,"y":58.536800384521484,"id":"13","attributes":{"comm":"1","year":"2014","author":"Markus V\u0026#246;lter","dblp_id":"5550483c45ce0a409eb6cc4d","description":"\u003ctable\u003e\u003ctr\u003e\u003ctd\u003eAuthor:\u003c/td\u003e\u003ctd\u003eMarkus V\u0026#246;lter\u003c/td\u003e\u003c/tr\u003e\u003ctr\u003e\u003ctd\u003eTitle:\u003c/td\u003e\u003ctd\u003eTowards User-Friendly Projectional Editors.\u003c/td\u003e\u003c/tr\u003e\u003ctr\u003e\u003ctd\u003eSource:\u003c/td\u003e\u003ctd\u003eSLE\u003c/td\u003e\u003c/tr\u003e\u003ctr\u003e\u003ctd\u003eYear:\u003c/td\u003e\u003ctd\u003e2014\u003c/td\u003e\u003c/tr\u003e\u003c/table\u003e","Cluster":"1","main":"1","title":"Towards User-Friendly Projectional Editors.","url":"http://dx.doi.org/10.1007/978-3-319-11245-9_3"},"color":"rgb(95,198,19)","size":23.846153259277344},{"label":"Omar (2017)","x":-100.34680938720703,"y":125.77598571777344,"id":"20","attributes":{"comm":"1","year":"2017","author":"Cyrus Omar","dblp_id":"57a4e91dac44365e35c98aab","description":"\u003ctable\u003e\u003ctr\u003e\u003ctd\u003eAuthor:\u003c/td\u003e\u003ctd\u003eCyrus Omar\u003c/td\u003e\u003c/tr\u003e\u003ctr\u003e\u003ctd\u003eTitle:\u003c/td\u003e\u003ctd\u003eHazelnut: A Bidirectionally Typed Structure Editor Calculus.\u003c/td\u003e\u003c/tr\u003e\u003ctr\u003e\u003ctd\u003eSource:\u003c/td\u003e\u003ctd\u003ePOPL\u003c/td\u003e\u003c/tr\u003e\u003ctr\u003e\u003ctd\u003eYear:\u003c/td\u003e\u003ctd\u003e2017\u003c/td\u003e\u003c/tr\u003e\u003c/table\u003e","Cluster":"0","main":"1","title":"Hazelnut: A Bidirectionally Typed Structure Editor Calculus.","url":"http://dx.doi.org/10.1145/3009837.3009900"},"color":"rgb(198,134,233)","size":13.076923370361328},{"label":"Syrel (2017)","x":-142.31088256835938,"y":106.66744995117188,"id":"29","attributes":{"comm":"1","year":"2017","author":"Aliaksei Syrel","dblp_id":"599f25cc9c057043f6de362a","description":"\u003ctable\u003e\u003ctr\u003e\u003ctd\u003eAuthor:\u003c/td\u003e\u003ctd\u003eAliaksei Syrel\u003c/td\u003e\u003c/tr\u003e\u003ctr\u003e\u003ctd\u003eTitle:\u003c/td\u003e\u003ctd\u003eTowards a live, moldable code editor\u003c/td\u003e\u003c/tr\u003e\u003ctr\u003e\u003ctd\u003eSource:\u003c/td\u003e\u003ctd\u003eProgramming\u003c/td\u003e\u003c/tr\u003e\u003ctr\u003e\u003ctd\u003eYear:\u003c/td\u003e\u003ctd\u003e2017\u003c/td\u003e\u003c/tr\u003e\u003c/table\u003e","Cluster":"2","main":"1","title":"Towards a live, moldable code editor","url":"http://dx.doi.org/10.1145/3079368.3079376"},"color":"rgb(0,202,255)","size":13.076923370361328},{"label":"Nakano (2016)","x":-579.5259399414062,"y":889.1133422851562,"id":"32","attributes":{"comm":"4","year":"2016","author":"Marina Nakano","dblp_id":"58d83045d649053542fe8822","description":"\u003ctable\u003e\u003ctr\u003e\u003ctd\u003eAuthor:\u003c/td\u003e\u003ctd\u003eMarina Nakano\u003c/td\u003e\u003c/tr\u003e\u003ctr\u003e\u003ctd\u003eTitle:\u003c/td\u003e\u003ctd\u003eA Structure Editor for the English Language.\u003c/td\u003e\u003c/tr\u003e\u003ctr\u003e\u003ctd\u003eSource:\u003c/td\u003e\u003ctd\u003eNBiS\u003c/td\u003e\u003c/tr\u003e\u003ctr\u003e\u003ctd\u003eYear:\u003c/td\u003e\u003ctd\u003e2016\u003c/td\u003e\u003c/tr\u003e\u003c/table\u003e","Cluster":"5","main":"1","title":"A Structure Editor for the English Language.","url":"http://dx.doi.org/10.1109/NBiS.2016.38"},"color":"rgb(255,92,129)","size":10.0},{"label":"Reuling (2020)","x":-275.7322998046875,"y":-77.8275375366211,"id":"38","attributes":{"comm":"1","year":"2020","author":"Dennis Reuling","dblp_id":"5e412ac53a55aca0eb0645ec","description":"\u003ctable\u003e\u003ctr\u003e\u003ctd\u003eAuthor:\u003c/td\u003e\u003ctd\u003eDennis Reuling\u003c/td\u003e\u003c/tr\u003e\u003ctr\u003e\u003ctd\u003eTitle:\u003c/td\u003e\u003ctd\u003eTowards projectional editing for model-based SPLs.\u003c/td\u003e\u003c/tr\u003e\u003ctr\u003e\u003ctd\u003eSource:\u003c/td\u003e\u003ctd\u003eVaMoS\u003c/td\u003e\u003c/tr\u003e\u003ctr\u003e\u003ctd\u003eYear:\u003c/td\u003e\u003ctd\u003e2020\u003c/td\u003e\u003c/tr\u003e\u003c/table\u003e","Cluster":"1","main":"1","title":"Towards projectional editing for model-based SPLs.","url":"https://doi.org/10.1145/3377024.3377030"},"color":"rgb(95,198,19)","size":11.538461685180664},{"label":"Walkingshaw (2014)","x":-390.64599609375,"y":-79.05794525146484,"id":"28","attributes":{"comm":"1","year":"2014","author":"Eric Walkingshaw","dblp_id":"5550486c45ce0a409eb6e260","description":"\u003ctable\u003e\u003ctr\u003e\u003ctd\u003eAuthor:\u003c/td\u003e\u003ctd\u003eEric Walkingshaw\u003c/td\u003e\u003c/tr\u003e\u003ctr\u003e\u003ctd\u003eTitle:\u003c/td\u003e\u003ctd\u003eProjectional editing of variational software\u003c/td\u003e\u003c/tr\u003e\u003ctr\u003e\u003ctd\u003eSource:\u003c/td\u003e\u003ctd\u003eGPCE\u003c/td\u003e\u003c/tr\u003e\u003ctr\u003e\u003ctd\u003eYear:\u003c/td\u003e\u003ctd\u003e2014\u003c/td\u003e\u003c/tr\u003e\u003c/table\u003e","Cluster":"1","main":"1","title":"Projectional editing of variational software","url":"http://dx.doi.org/10.1145/2658761.2658766"},"color":"rgb(95,198,19)","size":10.0},{"label":"Hempel (2018)","x":39.005313873291016,"y":100.53843688964844,"id":"33","attributes":{"comm":"1","year":"2018","author":"Brian Hempel","dblp_id":"5b67b44817c44aac1c8602d9","description":"\u003ctable\u003e\u003ctr\u003e\u003ctd\u003eAuthor:\u003c/td\u003e\u003ctd\u003eBrian Hempel\u003c/td\u003e\u003c/tr\u003e\u003ctr\u003e\u003ctd\u003eTitle:\u003c/td\u003e\u003ctd\u003eDeuce: a lightweight user interface for structured editing.\u003c/td\u003e\u003c/tr\u003e\u003ctr\u003e\u003ctd\u003eSource:\u003c/td\u003e\u003ctd\u003eICSE\u003c/td\u003e\u003c/tr\u003e\u003ctr\u003e\u003ctd\u003eYear:\u003c/td\u003e\u003ctd\u003e2018\u003c/td\u003e\u003c/tr\u003e\u003c/table\u003e","Cluster":"0","main":"1","title":"Deuce: a lightweight user interface for structured editing.","url":"http://doi.acm.org/10.1145/3180155.3180165"},"color":"rgb(198,134,233)","size":11.538461685180664},{"label":"Gomolka (2011)","x":21.318391799926758,"y":225.8749542236328,"id":"8","attributes":{"comm":"1","year":"2011","author":"Andreas Gomolka","dblp_id":"53e9a603b7602d9702f33879","description":"\u003ctable\u003e\u003ctr\u003e\u003ctd\u003eAuthor:\u003c/td\u003e\u003ctd\u003eAndreas Gomolka\u003c/td\u003e\u003c/tr\u003e\u003ctr\u003e\u003ctd\u003eTitle:\u003c/td\u003e\u003ctd\u003eAdvances in Structure Editors - Do They Really Pay Off?\u003c/td\u003e\u003c/tr\u003e\u003ctr\u003e\u003ctd\u003eSource:\u003c/td\u003e\u003ctd\u003eENASE 2011: PROCEEDINGS OF THE 6TH INTERNATIONAL CONFERENCE ON EVALUATION OF NOVEL APPROACHES TO SOFTWARE ENGINEERING\u003c/td\u003e\u003c/tr\u003e\u003ctr\u003e\u003ctd\u003eYear:\u003c/td\u003e\u003ctd\u003e2011\u003c/td\u003e\u003c/tr\u003e\u003c/table\u003e","Cluster":"0","main":"1","title":"Advances in Structure Editors - Do They Really Pay Off?","url":""},"color":"rgb(198,134,233)","size":10.0}],"edges":[{"source":"6","target":"7","id":"230","attributes":{},"color":"rgb(198,134,233)","size":1.0},{"source":"33","target":"3","id":"269","attributes":{},"color":"rgb(198,134,233)","size":1.0},{"source":"27","target":"23","id":"259","attributes":{},"color":"rgb(95,198,19)","size":1.0},{"source":"19","target":"4","id":"244","attributes":{},"color":"rgb(198,134,233)","size":1.0},{"source":"23","target":"3","id":"251","attributes":{},"color":"rgb(146,166,126)","size":1.0},{"source":"24","target":"25","id":"253","attributes":{},"color":"rgb(95,198,19)","size":1.0},{"source":"4","target":"6","id":"227","attributes":{},"color":"rgb(198,134,233)","size":1.0},{"source":"30","target":"23","id":"264","attributes":{},"color":"rgb(95,198,19)","size":1.0},{"source":"39","target":"3","id":"280","attributes":{},"color":"rgb(146,166,126)","size":1.0},{"source":"7","target":"5","id":"233","attributes":{},"color":"rgb(198,134,233)","size":1.0},{"source":"36","target":"3","id":"275","attributes":{},"color":"rgb(198,134,233)","size":1.0},{"source":"6","target":"3","id":"231","attributes":{},"color":"rgb(198,134,233)","size":1.0},{"source":"16","target":"4","id":"242","attributes":{},"color":"rgb(198,134,233)","size":1.0},{"source":"26","target":"22","id":"256","attributes":{},"color":"rgb(46,144,114)","size":1.0},{"source":"40","target":"13","id":"283","attributes":{},"color":"rgb(95,198,19)","size":1.0},{"source":"0","target":"1","id":"223","attributes":{},"color":"rgb(234,134,21)","size":1.0},{"source":"20","target":"5","id":"248","attributes":{},"color":"rgb(198,134,233)","size":1.0},{"source":"2","target":"3","id":"224","attributes":{},"color":"rgb(198,134,233)","size":1.0},{"source":"39","target":"24","id":"281","attributes":{},"color":"rgb(95,198,19)","size":1.0},{"source":"4","target":"7","id":"228","attributes":{},"color":"rgb(198,134,233)","size":1.0},{"source":"9","target":"5","id":"235","attributes":{},"color":"rgb(198,134,233)","size":1.0},{"source":"10","target":"3","id":"236","attributes":{},"color":"rgb(99,168,244)","size":1.0},{"source":"27","target":"13","id":"260","attributes":{},"color":"rgb(95,198,19)","size":1.0},{"source":"33","target":"4","id":"268","attributes":{},"color":"rgb(198,134,233)","size":1.0},{"source":"4","target":"5","id":"226","attributes":{},"color":"rgb(198,134,233)","size":1.0},{"source":"31","target":"32","id":"267","attributes":{},"color":"rgb(255,92,129)","size":1.0},{"source":"38","target":"23","id":"277","attributes":{},"color":"rgb(95,198,19)","size":1.0},{"source":"40","target":"3","id":"284","attributes":{},"color":"rgb(146,166,126)","size":1.0},{"source":"20","target":"13","id":"247","attributes":{},"color":"rgb(146,166,126)","size":1.0},{"source":"4","target":"3","id":"229","attributes":{},"color":"rgb(198,134,233)","size":1.0},{"source":"27","target":"24","id":"257","attributes":{},"color":"rgb(95,198,19)","size":1.0},{"source":"39","target":"23","id":"279","attributes":{},"color":"rgb(95,198,19)","size":1.0},{"source":"36","target":"4","id":"274","attributes":{},"color":"rgb(198,134,233)","size":1.0},{"source":"20","target":"4","id":"246","attributes":{},"color":"rgb(198,134,233)","size":1.0},{"source":"38","target":"27","id":"278","attributes":{},"color":"rgb(95,198,19)","size":1.0},{"source":"30","target":"12","id":"266","attributes":{},"color":"rgb(95,198,19)","size":1.0},{"source":"24","target":"23","id":"254","attributes":{},"color":"rgb(95,198,19)","size":1.0},{"source":"34","target":"14","id":"271","attributes":{},"color":"rgb(0,202,255)","size":1.0},{"source":"30","target":"13","id":"265","attributes":{},"color":"rgb(95,198,19)","size":1.0},{"source":"41","target":"23","id":"286","attributes":{},"color":"rgb(95,198,19)","size":1.0},{"source":"41","target":"7","id":"287","attributes":{},"color":"rgb(146,166,126)","size":1.0},{"source":"12","target":"13","id":"238","attributes":{},"color":"rgb(95,198,19)","size":1.0},{"source":"15","target":"4","id":"241","attributes":{},"color":"rgb(99,168,244)","size":1.0},{"source":"21","target":"22","id":"249","attributes":{},"color":"rgb(46,144,114)","size":1.0},{"source":"18","target":"13","id":"243","attributes":{},"color":"rgb(95,198,19)","size":1.0},{"source":"29","target":"4","id":"263","attributes":{},"color":"rgb(99,168,244)","size":1.0},{"source":"34","target":"35","id":"270","attributes":{},"color":"rgb(0,202,255)","size":1.0},{"source":"19","target":"2","id":"245","attributes":{},"color":"rgb(198,134,233)","size":1.0},{"source":"37","target":"34","id":"276","attributes":{},"color":"rgb(0,202,255)","size":1.0},{"source":"40","target":"24","id":"285","attributes":{},"color":"rgb(95,198,19)","size":1.0},{"source":"23","target":"13","id":"250","attributes":{},"color":"rgb(95,198,19)","size":1.0},{"source":"27","target":"28","id":"258","attributes":{},"color":"rgb(95,198,19)","size":1.0},{"source":"40","target":"23","id":"282","attributes":{},"color":"rgb(95,198,19)","size":1.0},{"source":"41","target":"13","id":"288","attributes":{},"color":"rgb(95,198,19)","size":1.0},{"source":"11","target":"0","id":"237","attributes":{},"color":"rgb(234,134,21)","size":1.0},{"source":"14","target":"15","id":"239","attributes":{},"color":"rgb(0,202,255)","size":1.0},{"source":"29","target":"14","id":"261","attributes":{},"color":"rgb(0,202,255)","size":1.0},{"source":"34","target":"13","id":"272","attributes":{},"color":"rgb(47,200,137)","size":1.0},{"source":"3","target":"7","id":"225","attributes":{},"color":"rgb(198,134,233)","size":1.0},{"source":"34","target":"10","id":"273","attributes":{},"color":"rgb(0,202,255)","size":1.0},{"source":"14","target":"4","id":"240","attributes":{},"color":"rgb(99,168,244)","size":1.0},{"source":"7","target":"17","id":"232","attributes":{},"color":"rgb(198,134,233)","size":1.0},{"source":"29","target":"24","id":"262","attributes":{},"color":"rgb(47,200,137)","size":1.0},{"source":"24","target":"12","id":"252","attributes":{},"color":"rgb(95,198,19)","size":1.0},{"source":"41","target":"4","id":"289","attributes":{},"color":"rgb(146,166,126)","size":1.0},{"source":"24","target":"13","id":"255","attributes":{},"color":"rgb(95,198,19)","size":1.0},{"source":"8","target":"4","id":"234","attributes":{},"color":"rgb(198,134,233)","size":1.0}]}